Metadata-Version: 2.1
Name: odoo14-addon-account-move-fiscal-year
Version: 14.0.1.0.1
Summary: Display the fiscal year on journal entries/item
Home-page: https://github.com/OCA/account-financial-tools
Author: ACSONE SA/NV, Odoo Community Association (OCA)
Author-email: support@odoo-community.org
License: AGPL-3
Platform: UNKNOWN
Classifier: Programming Language :: Python
Classifier: Framework :: Odoo
Classifier: Framework :: Odoo :: 14.0
Classifier: License :: OSI Approved :: GNU Affero General Public License v3
Requires-Python: >=3.6
Requires-Dist: odoo14-addon-account-fiscal-year
Requires-Dist: odoo (<14.1dev,>=14.0a)
